{
  "sections": {
    "slideshow": {
      "type": "slideshow",
      "blocks": {
        "slide-0": {
          "type": "image",
          "settings": {
            "apply_overlay": true,
            "content_position": "bottomLeft",
            "subheading": "Slide title",
            "title": "Tell your story",
            "button_1_text": "",
            "button_1_link": "",
            "button_2_text": "",
            "button_2_link": ""
          }
        },
        "slide-1": {
          "type": "image",
          "settings": {
            "apply_overlay": true,
            "content_position": "bottomLeft",
            "subheading": "Slide title",
            "title": "Tell your story",
            "button_1_text": "",
            "button_1_link": "",
            "button_2_text": "",
            "button_2_link": ""
          }
        }
      },
      "block_order": [
        "slide-0",
        "slide-1"
      ],
      "settings": {
        "show_fullscreen": true,
        "show_arrow": false,
        "autoplay": true,
        "cycle_speed": 5,
        "text_color": "#ffffff",
        "button_color": "#363636",
        "button_background": "#ffffff"
      }
    },
    "featured-collections": {
      "type": "featured-collections",
      "blocks": {
        "featured-collection-0": {
          "type": "collection",
          "settings": {
            "collection": "",
            "title": "",
            "grid_items_count": 8,
            "button_text": "View all products"
          }
        }
      },
      "block_order": [
        "featured-collection-0"
      ],
      "settings": {
        "title": "Featured collection",
        "layout_mode": "grid",
        "show_product_info": true,
        "show_vendor": false,
        "show_color_swatch": false,
        "grid_mobile_items_per_row": "2",
        "grid_desktop_items_per_row": 4
      }
    },
    "collection-list": {
      "type": "collection-list",
      "blocks": {
        "collection-0": {
          "type": "collection",
          "settings": {
            "collection": "",
            "image_alignment": "center center",
            "content_position": "bottomLeft",
            "subheading": "Sub-heading",
            "title": "Collection name",
            "button_text": "View products",
            "button_link": "",
            "apply_overlay": true
          }
        },
        "collection-1": {
          "type": "collection",
          "settings": {
            "collection": "",
            "image_alignment": "center center",
            "content_position": "bottomLeft",
            "subheading": "Sub-heading",
            "title": "Collection name",
            "button_text": "View products",
            "button_link": "",
            "apply_overlay": true
          }
        },
        "collection-2": {
          "type": "collection",
          "settings": {
            "collection": "",
            "image_alignment": "center center",
            "content_position": "bottomLeft",
            "subheading": "Sub-heading",
            "title": "Collection name",
            "button_text": "View products",
            "button_link": "",
            "apply_overlay": true
          }
        }
      },
      "block_order": [
        "collection-0",
        "collection-1",
        "collection-2"
      ],
      "settings": {
        "image_size": "normal",
        "add_spacing": true,
        "expand_collection": false,
        "stack_on_mobile": true,
        "text_color": "#ffffff",
        "button_color": "#363636"
      }
    },
    "featured-product": {
      "type": "featured-product",
      "blocks": {
        "product-meta": {
          "type": "product_meta",
          "settings": {
            "show_vendor": true,
            "show_sku": false,
            "show_product_rating": false,
            "show_taxes_included": false
          }
        },
        "share-buttons": {
          "type": "share_buttons",
          "settings": {
          }
        },
        "variant-selector": {
          "type": "variant_selector",
          "settings": {
            "selector_mode": "dropdown",
            "show_color_swatch": false,
            "show_color_carousel": false,
            "size_chart": ""
          }
        },
        "buy-buttons": {
          "type": "buy_buttons",
          "settings": {
            "show_price_in_button": false,
            "show_payment_button": true
          }
        }
      },
      "block_order": [
        "product-meta",
        "share-buttons",
        "variant-selector",
        "buy-buttons"
      ],
      "settings": {
        "subheading": "",
        "title": "Featured product",
        "show_headings_on_mobile": true,
        "product": ""
      }
    },
    "timeline": {
      "type": "timeline",
      "blocks": {
        "item-0": {
          "type": "item",
          "settings": {
            "apply_overlay": true,
            "title": "2000",
            "subheading": "Sub-heading",
            "heading": "Heading",
            "content": "<p>Add your own custom content to give more information about your store, availability details...<\/p>"
          }
        },
        "item-1": {
          "type": "item",
          "settings": {
            "apply_overlay": true,
            "title": "2001",
            "subheading": "Sub-heading",
            "heading": "Heading",
            "content": "<p>Add your own custom content to give more information about your store, availability details...<\/p>"
          }
        },
        "item-2": {
          "type": "item",
          "settings": {
            "apply_overlay": true,
            "title": "2002",
            "subheading": "Sub-heading",
            "heading": "Heading",
            "content": "<p>Add your own custom content to give more information about your store, availability details...<\/p>"
          }
        }
      },
      "block_order": [
        "item-0",
        "item-1",
        "item-2"
      ],
      "settings": {
        "text_color": "#ffffff"
      }
    },
    "blog-posts": {
      "type": "blog-posts",
      "blocks": {
        "blog-0": {
          "type": "blog",
          "settings": {
            "blog": "news"
          }
        }
      },
      "block_order": [
        "blog-0"
      ],
      "settings": {
        "subheading": "",
        "title": "Featured article",
        "show_category": false,
        "button_link": "",
        "button_text": "View all articles"
      }
    },
    "shop-the-look": {
      "type": "shop-the-look",
      "blocks": {
        "look-0": {
          "type": "look",
          "settings": {
            "dot_style": "light",
            "product_1": "",
            "product_1_horizontal_position": 30,
            "product_1_vertical_position": 40,
            "product_2": "",
            "product_2_horizontal_position": 45,
            "product_2_vertical_position": 65,
            "product_3": "",
            "product_3_horizontal_position": 70,
            "product_3_vertical_position": 50
          }
        },
        "look-1": {
          "type": "look",
          "settings": {
            "dot_style": "light",
            "product_1": "",
            "product_1_horizontal_position": 25,
            "product_1_vertical_position": 45,
            "product_2": "",
            "product_2_horizontal_position": 55,
            "product_2_vertical_position": 30,
            "product_3": "",
            "product_3_horizontal_position": 65,
            "product_3_vertical_position": 60
          }
        }
      },
      "block_order": [
        "look-0",
        "look-1"
      ],
      "settings": {
        "subheading": "Shop",
        "title": "Our looks",
        "show_mobile_product_info": false
      }
    },
    "76a1a166-4902-4af7-8503-cef5395c3a12": {
      "type": "three-column",
      "blocks": {
        "1e7bb111-96b7-4707-813c-a96e94fdaf61": {
          "type": "Text",
          "settings": {
            "image": "shopify:\/\/shop_images\/logo_d8ce3ec3-3b36-45ca-a19b-457ab508d256_1.png",
            "title": "Nutritional Value",
            "desc": "Millet milk is a good source of vitamins, minerals, and antioxidants, and is naturally gluten-free, making it a great alternative for people with gluten intolerance"
          }
        },
        "d104ebc2-b69a-4186-a7d7-8e2eff9efd24": {
          "type": "Text",
          "settings": {
            "image": "shopify:\/\/shop_images\/logo_d8ce3ec3-3b36-45ca-a19b-457ab508d256_1.png",
            "title": "Nutritional Value",
            "desc": "Millet milk is a good source of vitamins, minerals, and antioxidants, and is naturally gluten-free, making it a great alternative for people with gluten intolerance"
          }
        },
        "ff049133-68b3-4042-ab4d-772736aaad71": {
          "type": "Text",
          "settings": {
            "image": "shopify:\/\/shop_images\/logo_d8ce3ec3-3b36-45ca-a19b-457ab508d256_1.png",
            "title": "Nutritional Value",
            "desc": "Millet milk is a good source of vitamins, minerals, and antioxidants, and is naturally gluten-free, making it a great alternative for people with gluten intolerance"
          }
        }
      },
      "block_order": [
        "1e7bb111-96b7-4707-813c-a96e94fdaf61",
        "d104ebc2-b69a-4186-a7d7-8e2eff9efd24",
        "ff049133-68b3-4042-ab4d-772736aaad71"
      ],
      "settings": {
        "title": "From smoothies to soups",
        "desc": "The Benefits of Millets and Plant-Based Milk: Better for You, Better for the Environment!"
      }
    },
    "e613ad79-2d51-47e8-968b-aad640e83297": {
      "type": "featured-logo",
      "blocks": {
        "ed58f301-3be7-4a76-8430-de01b90cf92d": {
          "type": "Logo",
          "settings": {
            "logo": "shopify:\/\/shop_images\/logo_d8ce3ec3-3b36-45ca-a19b-457ab508d256_1.png",
            "link": ""
          }
        },
        "28900588-0ef8-48e1-bff5-c6ce903dbdd8": {
          "type": "Logo",
          "settings": {
            "logo": "shopify:\/\/shop_images\/logo_d8ce3ec3-3b36-45ca-a19b-457ab508d256_1.png",
            "link": ""
          }
        },
        "28a60d7e-92ef-4223-9e1a-b0de1d4b4c18": {
          "type": "Logo",
          "settings": {
            "logo": "shopify:\/\/shop_images\/logo_d8ce3ec3-3b36-45ca-a19b-457ab508d256_1.png",
            "link": ""
          }
        }
      },
      "block_order": [
        "ed58f301-3be7-4a76-8430-de01b90cf92d",
        "28900588-0ef8-48e1-bff5-c6ce903dbdd8",
        "28a60d7e-92ef-4223-9e1a-b0de1d4b4c18"
      ],
      "settings": {
        "enabled_featured_logo": true,
        "title": ""
      }
    },
    "6150a18b-d8d7-49f1-bd60-dcc4303d2a8f": {
      "type": "background-overlay-text",
      "settings": {
        "bg_color": "",
        "content_title_01": "Lorem Ipsum is simply dummy text of the printing",
        "content_desc_01": "Lorem Ipsum is simply dummy text of the printing and typesetting industry. Lorem Ipsum has been the industry's standard dummy text ever since the 1500s, when an unknown printer took a galley of type and scrambled",
        "content_list_1_title_01": "Vitamin",
        "content_list_1_desc_01": "<li>A<\/li>\n<li>B1<\/li>\n<li>B2<\/li>\n<li>B12<\/li>\n<li>D<\/li>",
        "content_list_1_title_02": "Calcium",
        "content_list_1_desc_02": "<li>Ca<\/li>",
        "content_title_02": "",
        "content_desc_02": "Lorem Ipsum is simply dummy text of the printing and typesetting industry. Lorem Ipsum has been the industry's standard dummy text ever since the 1500s, when an unknown printer took a galley of type and scrambled",
        "content_list_2_title_01": "",
        "content_list_2_desc_01": "",
        "content_list_2_title_02": "",
        "content_list_2_desc_02": ""
      }
    }
  },
  "order": [
    "slideshow",
    "featured-collections",
    "collection-list",
    "featured-product",
    "timeline",
    "blog-posts",
    "shop-the-look",
    "76a1a166-4902-4af7-8503-cef5395c3a12",
    "e613ad79-2d51-47e8-968b-aad640e83297",
    "6150a18b-d8d7-49f1-bd60-dcc4303d2a8f"
  ]
}
